PapersBee/__init__.py
papersbee-0.0.1.dist-info/METADATA
papersbee-0.0.1.dist-info/WHEEL
papersbee-0.0.1.dist-info/RECORD
